amphetamine/__about__.py
amphetamine/__init__.py
amphetamine/algorithms/__init__.py
amphetamine/algorithms/kahn.py
amphetamine/algorithms/manacher.py
amphetamine/utils/__init__.py
amphetamine/utils/blindscribe.py
amphetamine/utils/core.py
amphetamine/utils/cryptex.py
amphetamine/utils/hot_reload.py
amphetamine/utils/listen.py
amphetamine/utils/note.py
amphetamine/utils/numeric.py
amphetamine/utils/portland.py
amphetamine/utils/pprint.py
amphetamine/utils/.ipynb_checkpoints/numeric-checkpoint.py
amphetamine/utils/llm/__init__.py
amphetamine/utils/llm/claude.py
amphetamine/utils/llm/interfaces.py
amphetamine/utils/llm/models.py
amphetamine-0.0.2.dist-info/METADATA
amphetamine-0.0.2.dist-info/WHEEL
amphetamine-0.0.2.dist-info/entry_points.txt
amphetamine-0.0.2.dist-info/RECORD
